{
	"name": "Node.js",

	"image": "mcr.microsoft.com/devcontainers/javascript-node:1-22-bookworm",

	// "features": {},

	// "forwardPorts": [],

	// "postCreateCommand": "yarn install",

	"customizations": {
		"vscode": {
			"extensions": [ // extensões do vscode
			  "esbenp.prettier-vscode", // ferramenta de formatação de código
			  "dbaeumer.vscode-eslint", // identificar e corrigir problemas no código.
			  "ms-azuretools.vscode-docker", // extensão do docker
			   "ms-vscode-remote.remote-containers", // extensão do remote containers
			   "github.vscode-github-actions", // github actions
			   "github.copilot", // github copilot
				"Angular.ng-template", // extensão do angular
			   "github.copilot-chat", // github copilot chat
			   "vscode-icons-team.vscode-icons" // ícones para pastas do vscode 
			]
		}
	}
}